__init__.py
joplin_mcp_server/__init__.py
joplin_mcp_server/entry.py
joplin_mcp_server/joplin_client.py
joplin_mcp_server-0.1.1.dist-info/licenses/LICENSE.md
joplin_mcp_server-0.1.1.dist-info/METADATA
joplin_mcp_server-0.1.1.dist-info/WHEEL
joplin_mcp_server-0.1.1.dist-info/entry_points.txt
joplin_mcp_server-0.1.1.dist-info/top_level.txt
joplin_mcp_server-0.1.1.dist-info/RECORD
